potatofield/__init__.py
potatofield/category.py
potatofield/db.py
potatofield/detail.py
potatofield/find.py
potatofield/make.py
potatofield/modify.py
potatofield/page.py
potatofield/plan.py
potatofield/potato.py
potatofield/remove.py
testlist001-2.0.0.dist-info/METADATA
testlist001-2.0.0.dist-info/RECORD
testlist001-2.0.0.dist-info/WHEEL
testlist001-2.0.0.dist-info/entry_points.txt
testlist001-2.0.0.dist-info/top_level.txt
