Metadata-Version: 2.1
Name: testlist001
Version: 2.0.0
Summary: pypi testing
Home-page: UNKNOWN
Author: UNKNOWN
Author-email: UNKNOWN
License: UNKNOWN
Platform: UNKNOWN
